widget_tweaks/__init__.py
widget_tweaks/models.py
widget_tweaks/tests.py
widget_tweaks/templatetags/__init__.py
widget_tweaks/templatetags/widget_tweaks.py
django_widget_tweaks-1.4.6.dist-info/LICENSE
django_widget_tweaks-1.4.6.dist-info/METADATA
django_widget_tweaks-1.4.6.dist-info/WHEEL
django_widget_tweaks-1.4.6.dist-info/top_level.txt
django_widget_tweaks-1.4.6.dist-info/RECORD
