Metadata-Version: 1.1
Name: django-widget-tweaks
Version: 1.4.6
Summary: Tweak the form field rendering in templates, not in python-level form definitions.
Home-page: https://github.com/jazzband/django-widget-tweaks
Author: Mikhail Korobov
Author-email: kmike84@gmail.com
License: MIT license
Platform: UNKNOWN
Classifier: Development Status :: 5 - Production/Stable
Classifier: Framework :: Django
Classifier: Intended Audience :: Developers
Classifier: License :: OSI Approved :: MIT License
Classifier: Programming Language :: Python
Classifier: Programming Language :: Python :: 3
Classifier: Programming Language :: Python :: 3.6
Classifier: Programming Language :: Python :: 3.7
Classifier: Programming Language :: Python :: 3.8
Classifier: Topic :: Software Development :: Libraries :: Python Modules
Requires: django (>=1.11)
